silentpush/__init__.py
silentpush/client.py
silentpush/params_builder.py
silentpush/url_builder.py
silentpush/utils.py
silentpush/validators.py
silentpush-0.0.3.dist-info/METADATA
silentpush-0.0.3.dist-info/WHEEL
silentpush-0.0.3.dist-info/licenses/LICENSE
silentpush-0.0.3.dist-info/RECORD
